{
  "name": "Climate Change and International Security",
  "title": "Climate Change and International Security | Academic Presentation",
  "description": "A comprehensive academic presentation analyzing the nexus of environmental degradation, resource scarcity, and global conflict.",
  "imageUrl": "https://prezento.am/p/climate-security-presentation/preview-og.png",
  "url": "https://prezento.am/p/climate-security-presentation",
  "projectType": "university_presentation",
  "category": "Academic",
  "previewMeta": {
    "title": "Climate Change and International Security",
    "description": "Analyzing the nexus of environmental degradation and global conflict.",
    "imageUrl": "https://prezento.am/p/climate-security-presentation/preview-og.png",
    "url": "https://prezento.am/p/climate-security-presentation"
  },
  "requestFramePermissions": [],
  "majorCapabilities": []
}